ironflow/__init__.py
ironflow/_version.py
ironflow/utils.py
ironflow/gui/__init__.py
ironflow/gui/base.py
ironflow/gui/browser.py
ironflow/gui/draws_widgets.py
ironflow/gui/gui.py
ironflow/gui/log.py
ironflow/gui/workflows/__init__.py
ironflow/gui/workflows/screen.py
ironflow/gui/workflows/boxes/__init__.py
ironflow/gui/workflows/boxes/base.py
ironflow/gui/workflows/boxes/flow.py
ironflow/gui/workflows/boxes/text_output.py
ironflow/gui/workflows/boxes/toolbar.py
ironflow/gui/workflows/boxes/user_input.py
ironflow/gui/workflows/boxes/node_interface/__init__.py
ironflow/gui/workflows/boxes/node_interface/control.py
ironflow/gui/workflows/boxes/node_interface/input_widgets.py
ironflow/gui/workflows/boxes/node_interface/representation.py
ironflow/gui/workflows/canvas_widgets/__init__.py
ironflow/gui/workflows/canvas_widgets/base.py
ironflow/gui/workflows/canvas_widgets/buttons.py
ironflow/gui/workflows/canvas_widgets/flow.py
ironflow/gui/workflows/canvas_widgets/layouts.py
ironflow/gui/workflows/canvas_widgets/nodes.py
ironflow/gui/workflows/canvas_widgets/ports.py
ironflow/model/__init__.py
ironflow/model/dtypes.py
ironflow/model/flow.py
ironflow/model/model.py
ironflow/model/node.py
ironflow/model/otypes.py
ironflow/model/port.py
ironflow/model/script.py
ironflow/model/session.py
ironflow/node_tools/__init__.py
ironflow/node_tools/main_widgets.py
ironflow/node_tools/input_widgets/__init__.py
ironflow/nodes/__init__.py
ironflow/nodes/array.py
ironflow/nodes/plot.py
ironflow/nodes/pyiron_atomistics.py
ironflow/nodes/standard.py
ironflow/nodes/deprecated/__init__.py
ironflow/nodes/deprecated/basic_operators.py
ironflow/nodes/deprecated/built_in.py
ironflow/nodes/deprecated/control_structures.py
ironflow/nodes/deprecated/flow_control.py
ironflow/nodes/deprecated/special_nodes.py
ironflow-0.1.0.dist-info/LICENSE
ironflow-0.1.0.dist-info/METADATA
ironflow-0.1.0.dist-info/WHEEL
ironflow-0.1.0.dist-info/top_level.txt
ironflow-0.1.0.dist-info/RECORD
